dpugen/__init__.py
dpugen/confbase.py
dpugen/confutils.py
dpugen/dash.py
dpugen/dflt_params.py
dpugen/sai.py
dpugen/dashgen/__init__.py
dpugen/dashgen/acl_group.py
dpugen/dashgen/acl_rule.py
dpugen/dashgen/dash_appliance_table.py
dpugen/dashgen/dash_eni_table.py
dpugen/dashgen/dash_route_rule_table.py
dpugen/dashgen/dash_route_table.py
dpugen/dashgen/dash_vnet_mapping_table.py
dpugen/dashgen/dash_vnet_table.py
dpugen/dashgen/prefix_tag.py
dpugen/dashgen/vpc.py
dpugen/dashgen/vpcmappingtypes.py
dpugen/saigen/__init__.py
dpugen/saigen/acl_group.py
dpugen/saigen/acl_rule.py
dpugen/saigen/address_maps.py
dpugen/saigen/direction_lookup.py
dpugen/saigen/enis.py
dpugen/saigen/inbound_routing.py
dpugen/saigen/outbound_ca_to_pa.py
dpugen/saigen/outbound_routing.py
dpugen/saigen/pa_validation.py
dpugen/saigen/routing_group.py
dpugen/saigen/vips.py
dpugen/saigen/vnets.py
dpugen-0.2.3.dist-info/LICENSE
dpugen-0.2.3.dist-info/METADATA
dpugen-0.2.3.dist-info/WHEEL
dpugen-0.2.3.dist-info/top_level.txt
dpugen-0.2.3.dist-info/RECORD
