Metadata-Version: 2.1
Name: dpugen
Version: 0.2.3
Summary: Multi-vendor DPU library to generate its configuration
Home-page: https://github.com/mgheorghe/dpugen
Author: Mircea Dan Gheorghe
Author-email: mircea-dan.gheorghe@keysight.com
Classifier: Programming Language :: Python
Classifier: Programming Language :: Python :: 3
Classifier: License :: OSI Approved :: MIT License
Classifier: Operating System :: OS Independent
Requires-Python: <4,>=2.7
License-File: LICENSE
Requires-Dist: ipaddress
Requires-Dist: macaddress
Requires-Dist: munch
Requires-Dist: orjson
